testtools_cli/__init__.py
testtools_cli/cli.py
testtools_cli/conf.py
testtools_cli/constant.py
testtools_cli/debug/debugger.py
testtools_cli/debug/model.py
testtools_cli/debug/util.py
testtools_cli/generator/__init__.py
testtools_cli/generator/scaffold_checker.py
testtools_cli/generator/scaffold_generator.py
testtools_cli/generator/template_generator.py
testtools_cli/generator/scaffold/__init__.py
testtools_cli/generator/scaffold/golang/.gitignore
testtools_cli/generator/scaffold/golang/README.md
testtools_cli/generator/scaffold/golang/check.sh
testtools_cli/generator/scaffold/golang/go.mod
testtools_cli/generator/scaffold/golang/go.sum
testtools_cli/generator/scaffold/golang/main.go
testtools_cli/generator/scaffold/golang/testtool.yaml
testtools_cli/generator/scaffold/golang/cmd/discover/discover.go
testtools_cli/generator/scaffold/golang/cmd/execute/execute.go
testtools_cli/generator/scaffold/golang/pkg/testcase/testcase.go
testtools_cli/generator/scaffold/golang/pkg/util/common.go
testtools_cli/generator/scaffold/golang/script/linux/env.sh
testtools_cli/generator/scaffold/golang/script/linux/install.sh
testtools_cli/generator/scaffold/golang/script/linux/run.sh
testtools_cli/generator/scaffold/golang/script/macos/env.sh
testtools_cli/generator/scaffold/golang/script/macos/install.sh
testtools_cli/generator/scaffold/golang/script/macos/run.sh
testtools_cli/generator/scaffold/golang/script/windows/env.ps1
testtools_cli/generator/scaffold/golang/script/windows/install.ps1
testtools_cli/generator/scaffold/golang/script/windows/run.ps1
testtools_cli/generator/scaffold/python/.gitignore
testtools_cli/generator/scaffold/python/README.md
testtools_cli/generator/scaffold/python/check.sh
testtools_cli/generator/scaffold/python/pyproject.toml
testtools_cli/generator/scaffold/python/requirements.txt
testtools_cli/generator/scaffold/python/testtool.yaml
testtools_cli/generator/scaffold/python/uv.lock
testtools_cli/generator/scaffold/python/script/linux/entry.sh
testtools_cli-0.2.19.dist-info/METADATA
testtools_cli-0.2.19.dist-info/WHEEL
testtools_cli-0.2.19.dist-info/entry_points.txt
testtools_cli-0.2.19.dist-info/licenses/LICENSE
testtools_cli-0.2.19.dist-info/RECORD
