Metadata-Version: 2.4
Name: testtools-cli
Version: 0.2.19
Summary: TestSolar TestTool CLI
Project-URL: repository, https://github.com/OpenTestSolar/testtools-cli
Author-email: asiazhang <asiazhang2002@gmail.com>
License: Apache License 2.0
License-File: LICENSE
Keywords: cli,testsolar
Classifier: Development Status :: 4 - Beta
Classifier: Intended Audience :: Developers
Classifier: Programming Language :: Python
Classifier: Programming Language :: Python :: 3
Classifier: Programming Language :: Python :: 3.9
Classifier: Programming Language :: Python :: 3.10
Classifier: Programming Language :: Python :: 3.11
Classifier: Programming Language :: Python :: 3.12
Requires-Python: >=3.9
Requires-Dist: pydantic-settings>=2.6.1
Requires-Dist: rich>=13.7.1
Requires-Dist: solar-registry>=0.3.27
Requires-Dist: typer>=0.12.3
Requires-Dist: urllib3==1.26.6
